{
  "version": "5.11.3",
  "flags": {},
  "shapes": [
    {
      "label": "sugarcane",
      "points": [
        [
          55.38461538461537,
          372.49999999999994
        ],
        [
          13.076923076923066,
          194.03846153846155
        ],
        [
          0.0,
          152.5
        ],
        [
          0.0,
          246.34615384615384
        ],
        [
          12.692307692307693,
          290.96153846153845
        ],
        [
          32.69230769230769,
          363.65384615384613
        ],
        [
          38.07692307692308,
          380.57692307692304
        ]
      ],
      "group_id": null,
      "description": "",
      "shape_type": "polygon",
      "flags": {},
      "mask": null
    },
    {
      "label": "sugarcane",
      "points": [
        [
          56.92307692307692,
          338.65384615384613
        ],
        [
          25.76923076923076,
          169.03846153846155
        ],
        [
          16.153846153846146,
          57.49999999999999
        ],
        [
          10.76923076923076,
          4.423076923076923
        ],
        [
          1.7763568394002505e-15,
          3.0334987593052114
        ],
        [
          0.3846153846153868,
          106.73076923076923
        ],
        [
          4.230769230769226,
          156.34615384615384
        ],
        [
          18.84615384615384,
          232.8846153846154
        ],
        [
          46.53846153846153,
          335.57692307692304
        ],
        [
          46.153846153846146,
          346.3461538461538
        ]
      ],
      "group_id": null,
      "description": "",
      "shape_type": "polygon",
      "flags": {},
      "mask": null
    },
    {
      "label": "sugarcane",
      "points": [
        [
          64.6153846153846,
          327.88461538461536
        ],
        [
          42.69230769230769,
          135.96153846153848
        ],
        [
          26.538461538461533,
          18.653846153846153
        ],
        [
          25.76923076923076,
          2.884615384615384
        ],
        [
          46.53846153846153,
          1.7307692307692306
        ],
        [
          58.46153846153847,
          113.65384615384615
        ],
        [
          67.3076923076923,
          216.73076923076923
        ],
        [
          78.46153846153847,
          294.4230769230769
        ],
        [
          81.53846153846153,
          325.1923076923077
        ],
        [
          61.53846153846153,
          325.1923076923077
        ]
      ],
      "group_id": null,
      "description": "",
      "shape_type": "polygon",
      "flags": {},
      "mask": null
    },
    {
      "label": "sugarcane",
      "points": [
        [
          220.38461538461542,
          320.1923076923077
        ],
        [
          213.0769230769231,
          179.42307692307693
        ],
        [
          213.46153846153845,
          92.5
        ],
        [
          211.9230769230769,
          37.11538461538461
        ],
        [
          214.23076923076923,
          7.884615384615385
        ],
        [
          221.9230769230769,
          1.7307692307692306
        ],
        [
          219.61538461538464,
          50.192307692307686
        ],
        [
          219.23076923076923,
          110.96153846153845
        ],
        [
          224.23076923076923,
          194.03846153846155
        ],
        [
          231.15384615384613,
          249.42307692307693
        ],
        [
          232.30769230769232,
          312.88461538461536
        ]
      ],
      "group_id": null,
      "description": "",
      "shape_type": "polygon",
      "flags": {},
      "mask": null
    },
    {
      "label": "sugarcane",
      "points": [
        [
          286.15384615384613,
          324.80769230769226
        ],
        [
          294.2307692307692,
          170.5769230769231
        ],
        [
          301.9230769230769,
          71.34615384615384
        ],
        [
          310.0,
          10.576923076923077
        ],
        [
          312.2664835164835,
          0.0
        ],
        [
          327.3076923076923,
          2.884615384615384
        ],
        [
          315.7692307692308,
          83.65384615384615
        ],
        [
          310.38461538461536,
          142.5
        ],
        [
          305.0,
          213.65384615384616
        ],
        [
          300.7692307692308,
          285.57692307692304
        ],
        [
          299.2307692307692,
          320.1923076923077
        ],
        [
          283.84615384615387,
          322.1153846153846
        ]
      ],
      "group_id": null,
      "description": "",
      "shape_type": "polygon",
      "flags": {},
      "mask": null
    },
    {
      "label": "sugarcane",
      "points": [
        [
          301.15384615384613,
          357.1153846153846
        ],
        [
          312.3076923076923,
          261.7307692307692
        ],
        [
          326.15384615384613,
          96.34615384615384
        ],
        [
          328.84615384615387,
          57.88461538461538
        ],
        [
          333.84615384615387,
          32.11538461538461
        ],
        [
          335.7692307692308,
          4.423076923076923
        ],
        [
          337.9807692307692,
          0.0
        ],
        [
          349.61538461538464,
          2.115384615384615
        ],
        [
          343.84615384615387,
          52.88461538461538
        ],
        [
          335.38461538461536,
          119.8076923076923
        ],
        [
          332.6923076923077,
          168.65384615384616
        ],
        [
          325.0,
          235.57692307692307
        ],
        [
          316.9230769230769,
          290.57692307692304
        ],
        [
          312.3076923076923,
          340.1923076923077
        ],
        [
          310.7692307692308,
          354.4230769230769
        ]
      ],
      "group_id": null,
      "description": "",
      "shape_type": "polygon",
      "flags": {},
      "mask": null
    },
    {
      "label": "sugarcane",
      "points": [
        [
          414.6153846153846,
          339.4230769230769
        ],
        [
          421.92307692307696,
          226.73076923076923
        ],
        [
          429.99999999999994,
          111.34615384615384
        ],
        [
          439.2307692307692,
          0.1923076923076923
        ],
        [
          448.84615384615387,
          0.5769230769230769
        ],
        [
          440.7692307692308,
          157.1153846153846
        ],
        [
          432.3076923076923,
          256.7307692307692
        ],
        [
          425.3846153846154,
          324.4230769230769
        ],
        [
          424.99999999999994,
          335.57692307692304
        ]
      ],
      "group_id": null,
      "description": "",
      "shape_type": "polygon",
      "flags": {},
      "mask": null
    },
    {
      "label": "sugarcane",
      "points": [
        [
          503.4615384615385,
          339.0384615384615
        ],
        [
          475.7692307692308,
          213.26923076923077
        ],
        [
          472.3076923076923,
          146.73076923076923
        ],
        [
          472.6923076923077,
          74.42307692307692
        ],
        [
          475.3846153846154,
          20.576923076923077
        ],
        [
          476.15384615384613,
          1.346153846153846
        ],
        [
          493.84615384615387,
          2.115384615384615
        ],
        [
          487.6923076923077,
          62.88461538461538
        ],
        [
          483.84615384615387,
          133.65384615384616
        ],
        [
          483.84615384615387,
          202.5
        ],
        [
          494.2307692307692,
          259.0384615384615
        ],
        [
          505.7692307692308,
          321.3461538461538
        ],
        [
          508.84615384615387,
          337.1153846153846
        ]
      ],
      "group_id": null,
      "description": "",
      "shape_type": "polygon",
      "flags": {},
      "mask": null
    },
    {
      "label": "sugarcane",
      "points": [
        [
          544.2307692307692,
          317.1153846153846
        ],
        [
          540.7692307692307,
          187.1153846153846
        ],
        [
          539.6153846153845,
          76.34615384615384
        ],
        [
          538.8461538461538,
          10.961538461538462
        ],
        [
          539.9999999999999,
          0.1923076923076923
        ],
        [
          553.076923076923,
          2.115384615384615
        ],
        [
          547.6923076923076,
          79.03846153846153
        ],
        [
          549.9999999999999,
          183.65384615384616
        ],
        [
          552.6923076923076,
          280.96153846153845
        ],
        [
          554.2307692307692,
          316.3461538461538
        ],
        [
          539.2307692307692,
          314.80769230769226
        ]
      ],
      "group_id": null,
      "description": "",
      "shape_type": "polygon",
      "flags": {},
      "mask": null
    },
    {
      "label": "sugarcane",
      "points": [
        [
          576.5384615384614,
          337.88461538461536
        ],
        [
          571.1538461538461,
          176.73076923076923
        ],
        [
          579.9999999999999,
          111.73076923076923
        ],
        [
          581.1538461538461,
          25.96153846153846
        ],
        [
          581.1538461538461,
          9.038461538461538
        ],
        [
          581.9230769230769,
          3.269230769230769
        ],
        [
          593.076923076923,
          6.346153846153846
        ],
        [
          591.5384615384614,
          101.73076923076923
        ],
        [
          580.7692307692307,
          247.5
        ],
        [
          583.4615384615383,
          322.49999999999994
        ],
        [
          584.9999999999999,
          336.7307692307692
        ]
      ],
      "group_id": null,
      "description": "",
      "shape_type": "polygon",
      "flags": {},
      "mask": null
    },
    {
      "label": "sugarcane",
      "points": [
        [
          594.2307692307692,
          329.80769230769226
        ],
        [
          603.4615384615383,
          135.96153846153848
        ],
        [
          608.8461538461538,
          44.42307692307692
        ],
        [
          608.8461538461538,
          7.884615384615385
        ],
        [
          594.6153846153845,
          5.1923076923076925
        ],
        [
          588.4615384615383,
          148.65384615384616
        ],
        [
          582.3076923076923,
          255.57692307692307
        ],
        [
          586.1538461538461,
          331.7307692307692
        ]
      ],
      "group_id": null,
      "description": "",
      "shape_type": "polygon",
      "flags": {},
      "mask": null
    }
  ],
  "imagePath": "../right_sort/0008.png",
  "imageData": null,
  "imageHeight": 480,
  "imageWidth": 640
}