{
  "version": "5.11.3",
  "flags": {},
  "shapes": [
    {
      "label": "sugarcane",
      "points": [
        [
          494.2307692307692,
          378.65384615384613
        ],
        [
          502.6923076923077,
          331.7307692307692
        ],
        [
          517.3076923076924,
          252.8846153846154
        ],
        [
          528.8461538461538,
          220.5769230769231
        ],
        [
          538.4615384615385,
          159.03846153846155
        ],
        [
          546.1538461538462,
          117.88461538461537
        ],
        [
          568.8461538461538,
          15.576923076923077
        ],
        [
          584.2307692307693,
          9.038461538461538
        ],
        [
          555.0,
          152.5
        ],
        [
          544.2307692307693,
          227.8846153846154
        ],
        [
          526.1538461538462,
          286.3461538461538
        ],
        [
          515.7692307692308,
          336.7307692307692
        ],
        [
          505.7692307692308,
          379.0384615384615
        ]
      ],
      "group_id": null,
      "description": "",
      "shape_type": "polygon",
      "flags": {},
      "mask": null
    },
    {
      "label": "sugarcane",
      "points": [
        [
          471.92307692307685,
          384.0384615384615
        ],
        [
          484.99999999999994,
          329.0384615384615
        ],
        [
          499.6153846153846,
          275.57692307692304
        ],
        [
          515.0,
          201.34615384615384
        ],
        [
          525.0,
          134.03846153846155
        ],
        [
          535.0,
          146.34615384615384
        ],
        [
          531.5384615384615,
          183.65384615384616
        ],
        [
          518.0769230769231,
          249.42307692307693
        ],
        [
          500.3846153846153,
          318.65384615384613
        ],
        [
          489.6153846153846,
          367.88461538461536
        ],
        [
          482.3076923076923,
          387.88461538461536
        ],
        [
          476.92307692307685,
          384.80769230769226
        ]
      ],
      "group_id": null,
      "description": "",
      "shape_type": "polygon",
      "flags": {},
      "mask": null
    },
    {
      "label": "sugarcane",
      "points": [
        [
          477.3076923076923,
          363.2692307692307
        ],
        [
          483.07692307692304,
          281.3461538461538
        ],
        [
          487.3076923076923,
          214.80769230769232
        ],
        [
          495.3846153846153,
          198.26923076923077
        ],
        [
          505.7692307692308,
          204.42307692307693
        ],
        [
          499.6153846153846,
          270.1923076923077
        ],
        [
          496.15384615384613,
          286.7307692307692
        ],
        [
          486.5384615384615,
          320.1923076923077
        ],
        [
          481.5384615384615,
          339.0384615384615
        ],
        [
          477.6923076923077,
          354.0384615384615
        ]
      ],
      "group_id": null,
      "description": "",
      "shape_type": "polygon",
      "flags": {},
      "mask": null
    },
    {
      "label": "sugarcane",
      "points": [
        [
          581.1538461538462,
          359.0384615384615
        ],
        [
          593.0769230769231,
          291.3461538461538
        ],
        [
          605.3846153846154,
          209.03846153846155
        ],
        [
          611.9230769230769,
          134.80769230769232
        ],
        [
          620.7692307692308,
          119.42307692307692
        ],
        [
          621.5384615384615,
          146.34615384615384
        ],
        [
          616.9230769230769,
          199.03846153846155
        ],
        [
          614.6153846153846,
          246.73076923076923
        ],
        [
          600.0,
          312.88461538461536
        ],
        [
          592.3076923076923,
          345.96153846153845
        ],
        [
          588.4615384615385,
          362.49999999999994
        ]
      ],
      "group_id": null,
      "description": "",
      "shape_type": "polygon",
      "flags": {},
      "mask": null
    },
    {
      "label": "sugarcane",
      "points": [
        [
          593.8461538461538,
          364.0384615384615
        ],
        [
          617.6923076923077,
          252.8846153846154
        ],
        [
          626.5384615384615,
          216.34615384615384
        ],
        [
          636.1538461538462,
          165.5769230769231
        ],
        [
          639.0,
          192.52051282051275
        ],
        [
          628.4615384615385,
          275.57692307692304
        ],
        [
          610.0,
          343.2692307692307
        ],
        [
          607.6923076923077,
          367.49999999999994
        ],
        [
          603.4615384615385,
          384.80769230769226
        ],
        [
          598.8461538461538,
          397.88461538461536
        ],
        [
          595.0,
          413.65384615384613
        ],
        [
          588.0769230769231,
          426.7307692307692
        ],
        [
          579.2307692307693,
          423.2692307692307
        ],
        [
          578.4615384615385,
          412.49999999999994
        ],
        [
          586.5384615384615,
          396.3461538461538
        ]
      ],
      "group_id": null,
      "description": "",
      "shape_type": "polygon",
      "flags": {},
      "mask": null
    },
    {
      "label": "sugarcane",
      "points": [
        [
          330.7692307692307,
          386.7307692307692
        ],
        [
          338.8461538461538,
          276.7307692307692
        ],
        [
          344.23076923076917,
          212.5
        ],
        [
          348.46153846153845,
          135.96153846153848
        ],
        [
          349.23076923076917,
          87.11538461538461
        ],
        [
          351.5384615384615,
          54.03846153846153
        ],
        [
          363.8461538461538,
          36.34615384615384
        ],
        [
          361.9230769230769,
          84.42307692307692
        ],
        [
          360.7692307692307,
          151.34615384615384
        ],
        [
          354.99999999999994,
          222.8846153846154
        ],
        [
          354.23076923076917,
          252.1153846153846
        ],
        [
          350.7692307692307,
          289.0384615384615
        ],
        [
          344.6153846153846,
          344.4230769230769
        ],
        [
          340.38461538461536,
          387.1153846153846
        ]
      ],
      "group_id": null,
      "description": "",
      "shape_type": "polygon",
      "flags": {},
      "mask": null
    },
    {
      "label": "sugarcane",
      "points": [
        [
          285.38461538461536,
          396.7307692307692
        ],
        [
          299.6153846153846,
          254.03846153846155
        ],
        [
          307.6923076923077,
          172.1153846153846
        ],
        [
          312.30769230769226,
          119.03846153846153
        ],
        [
          314.99999999999994,
          90.57692307692307
        ],
        [
          322.30769230769226,
          68.26923076923076
        ],
        [
          330.38461538461536,
          76.73076923076923
        ],
        [
          323.46153846153845,
          144.03846153846155
        ],
        [
          312.6923076923077,
          235.96153846153845
        ],
        [
          304.6153846153846,
          308.2692307692307
        ],
        [
          297.30769230769226,
          397.1153846153846
        ],
        [
          293.46153846153845,
          410.96153846153845
        ],
        [
          282.30769230769226,
          401.7307692307692
        ]
      ],
      "group_id": null,
      "description": "",
      "shape_type": "polygon",
      "flags": {},
      "mask": null
    },
    {
      "label": "sugarcane",
      "points": [
        [
          263.07692307692304,
          393.65384615384613
        ],
        [
          277.6923076923077,
          394.0384615384615
        ],
        [
          283.46153846153845,
          336.7307692307692
        ],
        [
          284.6153846153846,
          294.80769230769226
        ],
        [
          288.8461538461538,
          257.5
        ],
        [
          291.15384615384613,
          216.73076923076923
        ],
        [
          289.99999999999994,
          158.65384615384616
        ],
        [
          288.46153846153845,
          114.03846153846153
        ],
        [
          289.99999999999994,
          82.5
        ],
        [
          290.38461538461536,
          58.653846153846146
        ],
        [
          290.38461538461536,
          40.96153846153846
        ],
        [
          278.07692307692304,
          38.653846153846146
        ],
        [
          273.46153846153845,
          122.49999999999999
        ],
        [
          274.23076923076917,
          189.80769230769232
        ],
        [
          271.5384615384615,
          257.1153846153846
        ],
        [
          268.07692307692304,
          333.65384615384613
        ],
        [
          266.15384615384613,
          377.1153846153846
        ]
      ],
      "group_id": null,
      "description": "",
      "shape_type": "polygon",
      "flags": {},
      "mask": null
    },
    {
      "label": "sugarcane",
      "points": [
        [
          251.92307692307693,
          379.80769230769226
        ],
        [
          262.6923076923077,
          382.49999999999994
        ],
        [
          268.46153846153845,
          241.73076923076923
        ],
        [
          269.6153846153846,
          174.42307692307693
        ],
        [
          273.07692307692304,
          142.8846153846154
        ],
        [
          271.9230769230769,
          113.65384615384615
        ],
        [
          271.9230769230769,
          87.11538461538461
        ],
        [
          262.30769230769226,
          80.57692307692307
        ],
        [
          253.84615384615384,
          110.96153846153845
        ],
        [
          252.6923076923077,
          176.34615384615384
        ],
        [
          253.84615384615384,
          197.1153846153846
        ],
        [
          254.6153846153846,
          220.5769230769231
        ],
        [
          253.07692307692307,
          245.96153846153845
        ],
        [
          251.15384615384616,
          274.4230769230769
        ],
        [
          250.76923076923075,
          297.1153846153846
        ],
        [
          250.3846153846154,
          332.1153846153846
        ],
        [
          250.76923076923075,
          346.3461538461538
        ],
        [
          251.92307692307693,
          364.0384615384615
        ]
      ],
      "group_id": null,
      "description": "",
      "shape_type": "polygon",
      "flags": {},
      "mask": null
    },
    {
      "label": "sugarcane",
      "points": [
        [
          133.84615384615384,
          377.49999999999994
        ],
        [
          147.69230769230768,
          380.96153846153845
        ],
        [
          153.84615384615384,
          285.1923076923077
        ],
        [
          153.46153846153845,
          249.03846153846155
        ],
        [
          154.6153846153846,
          235.1923076923077
        ],
        [
          158.84615384615384,
          213.26923076923077
        ],
        [
          157.69230769230768,
          197.8846153846154
        ],
        [
          157.69230769230768,
          178.65384615384616
        ],
        [
          158.07692307692307,
          167.5
        ],
        [
          157.69230769230768,
          155.96153846153848
        ],
        [
          156.92307692307693,
          134.80769230769232
        ],
        [
          156.53846153846155,
          117.49999999999999
        ],
        [
          156.53846153846155,
          104.8076923076923
        ],
        [
          156.15384615384616,
          90.57692307692307
        ],
        [
          156.15384615384616,
          68.65384615384615
        ],
        [
          143.46153846153845,
          73.65384615384615
        ],
        [
          141.53846153846155,
          105.57692307692307
        ],
        [
          142.30769230769232,
          112.88461538461537
        ],
        [
          142.30769230769232,
          129.42307692307693
        ],
        [
          141.92307692307693,
          146.73076923076923
        ],
        [
          141.92307692307693,
          173.65384615384616
        ],
        [
          142.69230769230768,
          187.8846153846154
        ],
        [
          143.46153846153845,
          193.65384615384616
        ],
        [
          143.84615384615384,
          207.1153846153846
        ],
        [
          144.23076923076923,
          214.03846153846155
        ],
        [
          142.69230769230768,
          228.26923076923077
        ],
        [
          142.30769230769232,
          243.26923076923077
        ],
        [
          139.6153846153846,
          253.26923076923077
        ],
        [
          139.6153846153846,
          263.65384615384613
        ],
        [
          139.6153846153846,
          280.96153846153845
        ],
        [
          140.0,
          292.1153846153846
        ],
        [
          140.3846153846154,
          302.88461538461536
        ],
        [
          140.0,
          318.65384615384613
        ],
        [
          134.6153846153846,
          364.80769230769226
        ]
      ],
      "group_id": null,
      "description": "",
      "shape_type": "polygon",
      "flags": {},
      "mask": null
    },
    {
      "label": "sugarcane",
      "points": [
        [
          102.69230769230768,
          371.7307692307692
        ],
        [
          119.61538461538461,
          374.0384615384615
        ],
        [
          118.07692307692307,
          308.2692307692307
        ],
        [
          114.61538461538461,
          201.73076923076923
        ],
        [
          116.92307692307693,
          156.73076923076923
        ],
        [
          119.23076923076923,
          87.11538461538461
        ],
        [
          121.53846153846155,
          40.192307692307686
        ],
        [
          124.61538461538461,
          10.576923076923077
        ],
        [
          122.30769230769232,
          1.7307692307692306
        ],
        [
          105.76923076923077,
          2.5
        ],
        [
          104.61538461538461,
          20.192307692307693
        ],
        [
          105.0,
          66.34615384615384
        ],
        [
          105.38461538461539,
          89.42307692307692
        ],
        [
          102.69230769230768,
          135.96153846153848
        ],
        [
          101.15384615384616,
          185.5769230769231
        ],
        [
          100.76923076923077,
          214.80769230769232
        ],
        [
          100.38461538461539,
          261.3461538461538
        ],
        [
          102.69230769230768,
          313.65384615384613
        ]
      ],
      "group_id": null,
      "description": "",
      "shape_type": "polygon",
      "flags": {},
      "mask": null
    },
    {
      "label": "sugarcane",
      "points": [
        [
          76.92307692307693,
          355.1923076923077
        ],
        [
          93.46153846153845,
          357.88461538461536
        ],
        [
          92.30769230769232,
          292.5
        ],
        [
          93.07692307692307,
          241.34615384615384
        ],
        [
          92.30769230769232,
          210.1923076923077
        ],
        [
          92.30769230769232,
          133.65384615384616
        ],
        [
          89.23076923076923,
          112.11538461538461
        ],
        [
          81.53846153846155,
          110.96153846153845
        ],
        [
          82.30769230769232,
          163.65384615384616
        ],
        [
          78.07692307692307,
          235.1923076923077
        ],
        [
          79.61538461538461,
          262.1153846153846
        ],
        [
          78.07692307692307,
          310.57692307692304
        ]
      ],
      "group_id": null,
      "description": "",
      "shape_type": "polygon",
      "flags": {},
      "mask": null
    },
    {
      "label": "sugarcane",
      "points": [
        [
          438.07692307692304,
          400.1923076923077
        ],
        [
          440.7692307692307,
          356.7307692307692
        ],
        [
          453.07692307692304,
          280.96153846153845
        ],
        [
          453.4615384615384,
          253.65384615384616
        ],
        [
          464.2307692307692,
          186.73076923076923
        ],
        [
          470.3846153846153,
          134.80769230769232
        ],
        [
          472.3076923076923,
          92.5
        ],
        [
          475.3846153846153,
          55.96153846153845
        ],
        [
          477.3076923076923,
          32.88461538461538
        ],
        [
          489.2307692307692,
          35.96153846153846
        ],
        [
          486.15384615384613,
          86.34615384615384
        ],
        [
          479.99999999999994,
          148.65384615384616
        ],
        [
          472.6923076923077,
          201.34615384615384
        ],
        [
          463.84615384615375,
          258.2692307692307
        ],
        [
          458.07692307692304,
          305.1923076923077
        ],
        [
          449.99999999999994,
          355.96153846153845
        ],
        [
          447.30769230769226,
          399.0384615384615
        ]
      ],
      "group_id": null,
      "description": "",
      "shape_type": "polygon",
      "flags": {},
      "mask": null
    },
    {
      "label": "sugarcane",
      "points": [
        [
          422.6923076923077,
          402.88461538461536
        ],
        [
          431.9230769230769,
          406.7307692307692
        ],
        [
          449.23076923076917,
          293.65384615384613
        ],
        [
          458.07692307692304,
          219.80769230769232
        ],
        [
          465.7692307692308,
          136.34615384615384
        ],
        [
          467.6923076923077,
          101.73076923076923
        ],
        [
          471.5384615384615,
          78.26923076923076
        ],
        [
          459.99999999999994,
          74.42307692307692
        ],
        [
          452.6923076923077,
          141.73076923076923
        ],
        [
          450.38461538461536,
          158.26923076923077
        ],
        [
          447.6923076923077,
          201.73076923076923
        ],
        [
          441.9230769230769,
          252.5
        ],
        [
          433.07692307692304,
          290.96153846153845
        ],
        [
          431.5384615384615,
          324.0384615384615
        ],
        [
          428.4615384615384,
          346.3461538461538
        ],
        [
          427.6923076923077,
          364.4230769230769
        ],
        [
          424.6153846153846,
          391.3461538461538
        ],
        [
          421.9230769230769,
          402.49999999999994
        ]
      ],
      "group_id": null,
      "description": "",
      "shape_type": "polygon",
      "flags": {},
      "mask": null
    },
    {
      "label": "sugarcane",
      "points": [
        [
          6.153846153846153,
          335.57692307692304
        ],
        [
          9.999999999999993,
          254.42307692307693
        ],
        [
          3.8461538461538467,
          198.65384615384616
        ],
        [
          1.1538461538461533,
          162.8846153846154
        ],
        [
          0.7692307692307665,
          336.3461538461538
        ]
      ],
      "group_id": null,
      "description": "",
      "shape_type": "polygon",
      "flags": {},
      "mask": null
    }
  ],
  "imagePath": "../right_sort/0060.png",
  "imageData": null,
  "imageHeight": 480,
  "imageWidth": 640
}